{
  "publicPath": "/blog/",
  "all": [
    "assets/css/0.styles.9305670d.css",
    "assets/img/search.83621669.svg",
    "assets/js/10.51f275f7.js",
    "assets/js/2.51a88660.js",
    "assets/js/3.263f9bb9.js",
    "assets/js/4.3d860504.js",
    "assets/js/5.2d028253.js",
    "assets/js/6.49e549a4.js",
    "assets/js/7.c281ca0a.js",
    "assets/js/8.47dbc7ce.js",
    "assets/js/9.f6700f8c.js",
    "assets/js/app.e9472b8b.js"
  ],
  "initial": [
    "assets/css/0.styles.9305670d.css",
    "assets/js/app.e9472b8b.js"
  ],
  "async": [
    "assets/js/10.51f275f7.js",
    "assets/js/2.51a88660.js",
    "assets/js/3.263f9bb9.js",
    "assets/js/4.3d860504.js",
    "assets/js/5.2d028253.js",
    "assets/js/6.49e549a4.js",
    "assets/js/7.c281ca0a.js",
    "assets/js/8.47dbc7ce.js",
    "assets/js/9.f6700f8c.js"
  ],
  "modules": {
    "20137146": [
      11
    ],
    "33579554": [
      11
    ],
    "38281294": [
      11
    ],
    "41237468": [
      11
    ],
    "47692828": [
      3,
      1
    ],
    "49098994": [
      3,
      1
    ],
    "56088668": [
      11
    ],
    "64590816": [
      11
    ],
    "71561453": [
      11
    ],
    "678cecd2": [
      11
    ],
    "7a984324": [
      11
    ],
    "3f909402": [
      11
    ],
    "6ba84170": [
      11
    ],
    "1d9e25be": [
      11
    ],
    "69a77738": [
      11
    ],
    "8cef4d82": [
      11
    ],
    "5abd29c9": [
      11
    ],
    "3780f012": [
      11
    ],
    "cb0b2d44": [
      11
    ],
    "f3ce6f46": [
      11
    ],
    "3e9c7fc2": [
      11
    ],
    "1b7f859c": [
      11
    ],
    "4503302b": [
      11
    ],
    "55ca15ae": [
      11
    ],
    "77adaf7c": [
      11
    ],
    "4696ced8": [
      11
    ],
    "4f08208e": [
      11
    ],
    "3eacf380": [
      11
    ],
    "9e4d8df0": [
      11
    ],
    "72f9f4f2": [
      11
    ],
    "164d8683": [
      11
    ],
    "0a22d5f5": [
      11
    ],
    "656f0745": [
      11
    ],
    "9cd8a960": [
      11
    ],
    "462377de": [
      11
    ],
    "1ae0dd71": [
      11
    ],
    "72eb86ac": [
      11
    ],
    "fc59a8cc": [
      11
    ],
    "305d93a9": [
      11
    ],
    "5966450f": [
      11
    ],
    "63df2850": [
      11
    ],
    "9803b816": [
      11
    ],
    "bf0677ce": [
      11
    ],
    "7d6e630c": [
      11
    ],
    "6df431be": [
      11
    ],
    "955b25d6": [
      11
    ],
    "aa88b360": [
      11
    ],
    "4f7e6d12": [
      11
    ],
    "4edb6db4": [
      11
    ],
    "18d20d67": [
      11
    ],
    "8f83fc44": [
      11
    ],
    "671ebab1": [
      11
    ],
    "6b962934": [
      11
    ],
    "4bfeb2d4": [
      11
    ],
    "790003a1": [
      11
    ],
    "b7a47f42": [
      11
    ],
    "14d76374": [
      11
    ],
    "7252ab3e": [
      11
    ],
    "28e059a2": [
      11
    ],
    "06db0fd8": [
      11
    ],
    "09c282c2": [
      11
    ],
    "254beeba": [
      11
    ],
    "1803246c": [
      11
    ],
    "f8f23668": [
      11
    ],
    "285d10ac": [
      11
    ],
    "7d58786a": [
      11
    ],
    "57627d6e": [
      11
    ],
    "0fa9f8cc": [
      11
    ],
    "4e9f4a2e": [
      11
    ],
    "09d991d6": [
      11
    ],
    "1fe539be": [
      11
    ],
    "7dd16115": [
      11
    ],
    "6a157b1b": [
      11
    ],
    "3ac13587": [
      11
    ],
    "6de7a3ae": [
      11
    ],
    "54c76746": [
      11
    ],
    "2e43e19d": [
      11
    ],
    "4661d166": [
      11
    ],
    "e2be4e56": [
      11
    ],
    "560663ac": [
      11
    ],
    "62b38c0a": [
      11
    ],
    "4a03a152": [
      11
    ],
    "5371293c": [
      11
    ],
    "cdeb67d8": [
      11
    ],
    "00719a08": [
      11
    ],
    "3254b0f1": [
      11
    ],
    "0c19d9ab": [
      11
    ],
    "5bc5e078": [
      11
    ],
    "4ca47dbb": [
      11
    ],
    "2e7b7991": [
      11
    ],
    "fc3aae98": [
      11
    ],
    "5fae57a8": [
      11
    ],
    "5eac3290": [
      11
    ],
    "4b6029fc": [
      11
    ],
    "9b1d6abe": [
      11
    ],
    "6c95f83b": [
      11
    ],
    "bf968aa2": [
      11
    ],
    "76d8385a": [
      11
    ],
    "5565694e": [
      11
    ],
    "e16296f2": [
      11
    ],
    "36ba2bd4": [
      11
    ],
    "ee0362fc": [
      11
    ],
    "b5d54172": [
      11
    ],
    "b8786ff0": [
      11
    ],
    "dab645cc": [
      11
    ],
    "0f90b598": [
      11
    ],
    "4cbc8ebc": [
      11
    ],
    "7108a069": [
      11
    ],
    "60e616d9": [
      11
    ],
    "35a6af28": [
      11
    ],
    "f0847a9c": [
      11
    ],
    "e278bc18": [
      11
    ],
    "9b6f1a42": [
      11
    ],
    "3e1b2563": [
      11
    ],
    "5f8b9c55": [
      11
    ],
    "1d1ae340": [
      11
    ],
    "b77d06f4": [
      11
    ],
    "0c117c63": [
      11
    ],
    "6b6337a5": [
      11
    ],
    "084c4f10": [
      11
    ],
    "31b021c4": [
      11
    ],
    "3b5e51dc": [
      11
    ],
    "b549bdfe": [
      11
    ],
    "d3c0d20e": [
      11
    ],
    "e4945e3c": [
      11
    ],
    "2918975a": [
      11
    ],
    "c3c45618": [
      11
    ],
    "a1d713a4": [
      11
    ],
    "4c1e3a9a": [
      11
    ],
    "77cdaf26": [
      11
    ],
    "1346f0ae": [
      11
    ],
    "72ca0329": [
      11
    ],
    "36f74414": [
      11
    ],
    "647fca8a": [
      11
    ],
    "94a778b4": [
      11
    ],
    "58495f26": [
      11
    ],
    "a7bb7b9e": [
      11
    ],
    "5796c5b2": [
      11
    ],
    "ad45c292": [
      11
    ],
    "158ea6b4": [
      11
    ],
    "1e96fdd1": [
      11
    ],
    "2681936c": [
      11
    ],
    "154453fc": [
      11
    ],
    "31c1a15a": [
      11
    ],
    "41fb97e2": [
      11
    ],
    "1d619a86": [
      11
    ],
    "2f4312cf": [
      11
    ],
    "4ceb2c70": [
      11
    ],
    "b306b6b6": [
      11
    ],
    "0849006f": [
      11
    ],
    "25c751e8": [
      11
    ],
    "256a0892": [
      11
    ],
    "037cc3bc": [
      11
    ],
    "703d97be": [
      11
    ],
    "84e62d34": [
      11
    ],
    "26f54fdd": [
      11
    ],
    "87bb89f2": [
      11
    ],
    "544d7492": [
      11
    ],
    "eaf57fb0": [
      11
    ],
    "7f3c84d8": [
      11
    ],
    "7960e1d2": [
      11
    ],
    "e74c2824": [
      11
    ],
    "a3608b1e": [
      11
    ],
    "4b147d5a": [
      11
    ],
    "6d0e460b": [
      11
    ],
    "95a204cc": [
      11
    ],
    "8ce98880": [
      11
    ],
    "9bcccbd4": [
      11
    ],
    "77d94e17": [
      11
    ],
    "5b5b3e60": [
      11
    ],
    "dcdc546e": [
      11
    ],
    "0c7bb24b": [
      11
    ],
    "48152b17": [
      11
    ],
    "1f6c4185": [
      11
    ],
    "37e9bfaa": [
      11
    ],
    "7cc96471": [
      11
    ],
    "95750c5a": [
      11
    ],
    "db8f1b9c": [
      11
    ],
    "0e005392": [
      11
    ],
    "e354c4c4": [
      11
    ],
    "610a2818": [
      11
    ],
    "647b6629": [
      11
    ],
    "2bf77747": [
      11
    ],
    "54b40ffb": [
      11
    ],
    "057387f4": [
      11
    ],
    "42c1d7f4": [
      11
    ],
    "86f95df4": [
      11
    ],
    "0cdaac52": [
      11
    ],
    "1538d0d9": [
      11
    ],
    "7d20a689": [
      11
    ],
    "fa8d0f64": [
      11
    ],
    "462731e9": [
      11
    ],
    "5669728c": [
      11
    ],
    "d5b686a8": [
      11
    ],
    "279695a2": [
      11
    ],
    "4f7a34fe": [
      11
    ],
    "5d400974": [
      11
    ],
    "518f394c": [
      11
    ],
    "26d0c3d4": [
      11
    ],
    "13806e97": [
      11
    ],
    "f3c0859e": [
      11
    ],
    "3ae78b54": [
      11
    ],
    "1db7f5f8": [
      11
    ],
    "6e5fda23": [
      11
    ],
    "76f86b66": [
      11
    ],
    "b52f5322": [
      11
    ],
    "5e955c6d": [
      11
    ],
    "0730b0c6": [
      11
    ],
    "637eb9dc": [
      11
    ],
    "e16d7756": [
      11
    ],
    "3dd5ab30": [
      11
    ],
    "d9cfa79a": [
      11
    ],
    "c21c33fc": [
      11
    ],
    "696d7e0e": [
      11
    ],
    "475398f4": [
      11
    ],
    "1f6cbb15": [
      11
    ],
    "049a2b41": [
      11
    ],
    "548c802c": [
      11
    ],
    "6906a7a0": [
      11
    ],
    "87b3f8ce": [
      11
    ],
    "01ec1986": [
      11
    ],
    "394619b0": [
      11
    ],
    "3ac21fec": [
      11
    ],
    "4dc04124": [
      11
    ],
    "4dcf278c": [
      11
    ],
    "18e89cae": [
      11
    ],
    "e644c7e8": [
      11
    ],
    "50369afa": [
      11
    ],
    "168bef2e": [
      11
    ],
    "9b91f0a0": [
      11
    ],
    "098bb271": [
      11
    ],
    "5e5a1f65": [
      11
    ],
    "750cc2f0": [
      11
    ],
    "7214b678": [
      11
    ],
    "4c187408": [
      11
    ],
    "4e12ef26": [
      11
    ],
    "401c6aa1": [
      11
    ],
    "5c95db00": [
      11
    ],
    "599dce88": [
      11
    ],
    "33a18c18": [
      11
    ],
    "d3d101aa": [
      11
    ],
    "292feae2": [
      11
    ],
    "1192fc14": [
      11
    ],
    "f52232ba": [
      11
    ],
    "123eaf0f": [
      11
    ],
    "36d9d783": [
      11
    ],
    "5e373908": [
      11
    ],
    "50e0e15e": [
      11
    ],
    "1ccae6ff": [
      11
    ],
    "15a2e02e": [
      11
    ],
    "0a584299": [
      11
    ],
    "53696cc2": [
      11
    ],
    "3fb0e89c": [
      11
    ],
    "5bcf03e8": [
      11
    ],
    "73b5659b": [
      11
    ],
    "5afaf8a8": [
      11
    ],
    "5f5501dc": [
      11
    ],
    "4db6770c": [
      11
    ],
    "08b85999": [
      11
    ],
    "2b4f6f50": [
      11
    ],
    "bad1705a": [
      11
    ],
    "138a3a64": [
      11
    ],
    "ac18aa0c": [
      11
    ],
    "5369e7a2": [
      11
    ],
    "5ae01415": [
      11
    ],
    "388b45cc": [
      11
    ],
    "840ae4b6": [
      11
    ],
    "ae3a160e": [
      11
    ],
    "16ff3366": [
      11
    ],
    "4fa5cb4e": [
      11
    ],
    "392e6343": [
      11
    ],
    "41dd7b65": [
      11
    ],
    "134d4721": [
      11
    ],
    "5ffc660a": [
      11
    ],
    "bff101c4": [
      11
    ],
    "12b4a63c": [
      11
    ],
    "05e0069e": [
      11
    ],
    "79b46948": [
      11
    ],
    "d6d4d1d0": [
      11
    ],
    "15f3820c": [
      11
    ],
    "7aafdfb9": [
      11
    ],
    "3f047056": [
      11
    ],
    "634059fc": [
      11
    ],
    "8d37327c": [
      11
    ],
    "48e8d91a": [
      11
    ],
    "13a081a6": [
      11
    ],
    "2e0ba02e": [
      11
    ],
    "3b365ca8": [
      11
    ],
    "282fe6ec": [
      11
    ],
    "8e553128": [
      11
    ],
    "258ca138": [
      11
    ],
    "4e5144e0": [
      11
    ],
    "8c51ae20": [
      11
    ],
    "6f248e46": [
      11
    ],
    "a49fbdac": [
      11
    ],
    "53aba0a2": [
      11
    ],
    "48eb1150": [
      11
    ],
    "1f2c83c4": [
      11
    ],
    "62870af8": [
      11
    ],
    "34bfb54c": [
      11
    ],
    "2447ad5e": [
      11
    ],
    "6d5b9b2d": [
      11
    ],
    "6ad8998b": [
      11
    ],
    "69e22fa2": [
      3,
      1
    ],
    "bd9a372c": [
      3,
      1
    ],
    "d8d852ba": [
      3,
      1
    ],
    "3f70a54d": [
      3,
      1
    ],
    "71c67a74": [
      3,
      1
    ],
    "43277ff8": [
      3,
      1
    ],
    "26c7e04a": [
      3,
      1
    ],
    "f9237f22": [
      3,
      1
    ],
    "7871449a": [
      3,
      1
    ],
    "47c0d67d": [
      3,
      1
    ],
    "e996dac4": [
      3,
      1
    ],
    "15f8575a": [
      3,
      1
    ],
    "ad137572": [
      3,
      1
    ],
    "44188f00": [
      3,
      1
    ],
    "c3cdb434": [
      3,
      1
    ],
    "7163de92": [
      4
    ],
    "1caaa6f5": [
      3,
      1
    ],
    "3fdeb185": [
      3,
      1
    ],
    "c7a80d86": [
      3,
      1
    ],
    "17ae541d": [
      3,
      1
    ],
    "fa90e214": [
      3,
      1
    ],
    "4a625ad8": [
      3,
      1
    ],
    "2c403ea1": [
      3,
      1
    ],
    "3437e336": [
      3,
      1
    ],
    "53d7ab47": [
      3,
      1
    ],
    "c98a9028": [
      3,
      1
    ],
    "60b20a37": [
      3,
      1
    ],
    "2241e4c7": [
      3,
      1
    ],
    "2f4db6da": [
      3,
      1
    ],
    "6a8f88ba": [
      3,
      1
    ],
    "4c3c6106": [
      3,
      1
    ],
    "7ffd9818": [
      3,
      1
    ],
    "f503954c": [
      3,
      1
    ],
    "33c812e4": [
      3,
      1
    ],
    "506a40de": [
      3,
      1
    ],
    "a78cbffa": [
      3,
      1
    ],
    "5d638e2e": [
      3,
      1
    ],
    "2cb32011": [
      3,
      1
    ],
    "a5a0dcd4": [
      3,
      1
    ],
    "58c8c68a": [
      3,
      1
    ],
    "7bbbf032": [
      3,
      1
    ],
    "5b7cb64a": [
      3,
      1
    ],
    "509d3a38": [
      3,
      1
    ],
    "c597d328": [
      3,
      1
    ],
    "6bad59d2": [
      3,
      1
    ],
    "5798f44b": [
      4
    ],
    "4c66b298": [
      3,
      1
    ],
    "48931dda": [
      5
    ],
    "0ff7df9c": [
      6
    ],
    "2d3b7755": [
      9
    ],
    "18af80fb": [
      7
    ],
    "0b82341b": [
      10
    ],
    "6a9441e0": [
      2
    ],
    "27590dfb": [
      8
    ],
    "4b2827c8": [
      4
    ],
    "412b39e7": [
      0,
      -1
    ],
    "331bf4a1": [
      0,
      -1
    ],
    "2d0790c8": [
      0,
      -1
    ],
    "0e263ef6": [
      0,
      -1
    ],
    "602a9196": [
      0,
      -1
    ],
    "7bf9f521": [
      0,
      -1
    ],
    "9f3bfedc": [
      0,
      -1
    ],
    "452c1a5e": [
      0,
      -1
    ],
    "21cf8ea8": [
      0,
      -1
    ],
    "042317c4": [
      0,
      -1
    ],
    "6b87f418": [
      0,
      -1
    ],
    "3ad785fb": [
      0,
      -1
    ],
    "0eeafb60": [
      0,
      -1
    ],
    "44e8cf3a": [
      0,
      -1
    ],
    "b6f5fe26": [
      0,
      -1
    ],
    "6ae5f476": [
      0,
      -1
    ],
    "5ae3f042": [
      0,
      -1
    ],
    "551fca48": [
      0,
      -1
    ]
  }
}